[
	{
		"__TYPE__": "SharedSliceContent",
		"variation": "default",
		"primary": {
			"prompt_text": {
				"__TYPE__": "StructuredTextContent",
				"value": [
					{
						"type": "paragraph",
						"content": {
							"text": "Inscrivez vous à notre newsletter",
							"spans": []
						},
						"direction": "ltr"
					}
				]
			},
			"placeholder_email": {
				"__TYPE__": "FieldContent",
				"type": "Text",
				"value": "votre@email.com"
			},
			"submit_action": {
				"key": "57d122b4-9131-40e0-9b02-d2e9d1856a59",
				"__TYPE__": "LinkContent",
				"value": {
					"__TYPE__": "ExternalLink",
					"url": "https://prismic.io"
				}
			}
		},
		"items": []
	}
]